[{"user_id": "e7ac0138-4d80-4400-9141-461daa6be8ae", "match_id": "03ecb8d2-38d1-47ef-b7fc-adbb5744d1a0", "map_id": "AmbroseValley", "x": -140.16, "z": -191.59, "px": 261.51, "py": 703.82, "ts": 1770887314, "event": "Position", "is_bot": false, "is_combat": false, "rel_ts": 0}, {"user_id": "e7ac0138-4d80-4400-9141-461daa6be8ae", "match_id": "03ecb8d2-38d1-47ef-b7fc-adbb5744d1a0", "map_id": "AmbroseValley", "x": -135.25, "z": -161.16, "px": 267.09, "py": 669.2, "ts": 1770887329, "event": "Position", "is_bot": false, "is_combat": false, "rel_ts": 15}, {"user_id": "e7ac0138-4d80-4400-9141-461daa6be8ae", "match_id": "03ecb8d2-38d1-47ef-b7fc-adbb5744d1a0", "map_id": "AmbroseValley", "x": -131.45, "z": -127.1, "px": 271.42, "py": 630.44, "ts": 1770887334, "event": "Position", "is_bot": false, "is_combat": false, "rel_ts": 20}, {"user_id": "e7ac0138-4d80-4400-9141-461daa6be8ae", "match_id": "03ecb8d2-38d1-47ef-b7fc-adbb5744d1a0", "map_id": "AmbroseValley", "x": -131.18, "z": -93.39, "px": 271.72, "py": 592.08, "ts": 1770887339, "event": "Position", "is_bot": false, "is_combat": false, "rel_ts": 25}, {"user_id": "e7ac0138-4d80-4400-9141-461daa6be8ae", "match_id": "03ecb8d2-38d1-47ef-b7fc-adbb5744d1a0", "map_id": "AmbroseValley", "x": -133.14, "z": -69.34, "px": 269.49, "py": 564.72, "ts": 1770887344, "event": "Position", "is_bot": false, "is_combat": false, "rel_ts": 30}, {"user_id": "e7ac0138-4d80-4400-9141-461daa6be8ae", "match_id": "03ecb8d2-38d1-47ef-b7fc-adbb5744d1a0", "map_id": "AmbroseValley", "x": -117.62, "z": -52.85, "px": 287.15, "py": 545.96, "ts": 1770887349, "event": "Position", "is_bot": false, "is_combat": false, "rel_ts": 35}, {"user_id": "e7ac0138-4d80-4400-9141-461daa6be8ae", "match_id": "03ecb8d2-38d1-47ef-b7fc-adbb5744d1a0", "map_id": "AmbroseValley", "x": -112.88, "z": -43.51, "px": 292.54, "py": 535.33, "ts": 1770887354, "event": "Position", "is_bot": false, "is_combat": false, "rel_ts": 40}, {"user_id": "e7ac0138-4d80-4400-9141-461daa6be8ae", "match_id": "03ecb8d2-38d1-47ef-b7fc-adbb5744d1a0", "map_id": "AmbroseValley", "x": -113.41, "z": -47.57, "px": 291.95, "py": 539.95, "ts": 1770887359, "event": "Position", "is_bot": false, "is_combat": false, "rel_ts": 45}, {"user_id": "e7ac0138-4d80-4400-9141-461daa6be8ae", "match_id": "03ecb8d2-38d1-47ef-b7fc-adbb5744d1a0", "map_id": "AmbroseValley", "x": -112.29, "z": -45.92, "px": 293.21, "py": 538.08, "ts": 1770887361, "event": "BotKilled", "is_bot": false, "is_combat": true, "rel_ts": 47}]