[{"user_id": "c830d8d5-e7c2-4d09-935e-d3c79c5903a1", "match_id": "203748c9-3fff-4d7f-83b8-22f0d9adc402", "map_id": "AmbroseValley", "x": -104.4, "z": -364.97, "px": 302.19, "py": 901.09, "ts": 1770780015, "event": "Position", "is_bot": false, "is_combat": false, "rel_ts": 0}, {"user_id": "c830d8d5-e7c2-4d09-935e-d3c79c5903a1", "match_id": "203748c9-3fff-4d7f-83b8-22f0d9adc402", "map_id": "AmbroseValley", "x": -86.48, "z": -356.07, "px": 322.58, "py": 890.96, "ts": 1770780025, "event": "Position", "is_bot": false, "is_combat": false, "rel_ts": 10}, {"user_id": "c830d8d5-e7c2-4d09-935e-d3c79c5903a1", "match_id": "203748c9-3fff-4d7f-83b8-22f0d9adc402", "map_id": "AmbroseValley", "x": -60.43, "z": -357.45, "px": 352.22, "py": 892.53, "ts": 1770780030, "event": "Position", "is_bot": false, "is_combat": false, "rel_ts": 15}, {"user_id": "c830d8d5-e7c2-4d09-935e-d3c79c5903a1", "match_id": "203748c9-3fff-4d7f-83b8-22f0d9adc402", "map_id": "AmbroseValley", "x": -54.24, "z": -356.9, "px": 359.26, "py": 891.9, "ts": 1770780032, "event": "Loot", "is_bot": false, "is_combat": true, "rel_ts": 17}, {"user_id": "c830d8d5-e7c2-4d09-935e-d3c79c5903a1", "match_id": "203748c9-3fff-4d7f-83b8-22f0d9adc402", "map_id": "AmbroseValley", "x": -52.73, "z": -358.85, "px": 360.99, "py": 894.13, "ts": 1770780033, "event": "Loot", "is_bot": false, "is_combat": true, "rel_ts": 18}, {"user_id": "c830d8d5-e7c2-4d09-935e-d3c79c5903a1", "match_id": "203748c9-3fff-4d7f-83b8-22f0d9adc402", "map_id": "AmbroseValley", "x": -53.08, "z": -356.86, "px": 360.59, "py": 891.86, "ts": 1770780035, "event": "Position", "is_bot": false, "is_combat": false, "rel_ts": 20}, {"user_id": "c830d8d5-e7c2-4d09-935e-d3c79c5903a1", "match_id": "203748c9-3fff-4d7f-83b8-22f0d9adc402", "map_id": "AmbroseValley", "x": -58.14, "z": -348.72, "px": 354.82, "py": 882.59, "ts": 1770780037, "event": "Loot", "is_bot": false, "is_combat": true, "rel_ts": 22}, {"user_id": "c830d8d5-e7c2-4d09-935e-d3c79c5903a1", "match_id": "203748c9-3fff-4d7f-83b8-22f0d9adc402", "map_id": "AmbroseValley", "x": -51.68, "z": -353.46, "px": 362.18, "py": 887.99, "ts": 1770780040, "event": "Position", "is_bot": false, "is_combat": false, "rel_ts": 25}, {"user_id": "c830d8d5-e7c2-4d09-935e-d3c79c5903a1", "match_id": "203748c9-3fff-4d7f-83b8-22f0d9adc402", "map_id": "AmbroseValley", "x": -46.34, "z": -356.0, "px": 368.25, "py": 890.88, "ts": 1770780045, "event": "Position", "is_bot": false, "is_combat": false, "rel_ts": 30}, {"user_id": "c830d8d5-e7c2-4d09-935e-d3c79c5903a1", "match_id": "203748c9-3fff-4d7f-83b8-22f0d9adc402", "map_id": "AmbroseValley", "x": -42.65, "z": -359.49, "px": 372.45, "py": 894.85, "ts": 1770780046, "event": "Loot", "is_bot": false, "is_combat": true, "rel_ts": 31}, {"user_id": "c830d8d5-e7c2-4d09-935e-d3c79c5903a1", "match_id": "203748c9-3fff-4d7f-83b8-22f0d9adc402", "map_id": "AmbroseValley", "x": -41.07, "z": -359.55, "px": 374.24, "py": 894.92, "ts": 1770780047, "event": "Loot", "is_bot": false, "is_combat": true, "rel_ts": 32}, {"user_id": "c830d8d5-e7c2-4d09-935e-d3c79c5903a1", "match_id": "203748c9-3fff-4d7f-83b8-22f0d9adc402", "map_id": "AmbroseValley", "x": -42.97, "z": -354.33, "px": 372.09, "py": 888.98, "ts": 1770780050, "event": "Position", "is_bot": false, "is_combat": false, "rel_ts": 35}, {"user_id": "c830d8d5-e7c2-4d09-935e-d3c79c5903a1", "match_id": "203748c9-3fff-4d7f-83b8-22f0d9adc402", "map_id": "AmbroseValley", "x": -42.97, "z": -354.33, "px": 372.09, "py": 888.98, "ts": 1770780050, "event": "Loot", "is_bot": false, "is_combat": true, "rel_ts": 35}, {"user_id": "c830d8d5-e7c2-4d09-935e-d3c79c5903a1", "match_id": "203748c9-3fff-4d7f-83b8-22f0d9adc402", "map_id": "AmbroseValley", "x": -32.58, "z": -353.01, "px": 383.91, "py": 887.48, "ts": 1770780055, "event": "Position", "is_bot": false, "is_combat": false, "rel_ts": 40}, {"user_id": "c830d8d5-e7c2-4d09-935e-d3c79c5903a1", "match_id": "203748c9-3fff-4d7f-83b8-22f0d9adc402", "map_id": "AmbroseValley", "x": -23.26, "z": -322.71, "px": 394.51, "py": 853.0, "ts": 1770780060, "event": "Position", "is_bot": false, "is_combat": false, "rel_ts": 45}, {"user_id": "c830d8d5-e7c2-4d09-935e-d3c79c5903a1", "match_id": "203748c9-3fff-4d7f-83b8-22f0d9adc402", "map_id": "AmbroseValley", "x": -15.87, "z": -295.16, "px": 402.92, "py": 821.66, "ts": 1770780065, "event": "Position", "is_bot": false, "is_combat": false, "rel_ts": 50}, {"user_id": "c830d8d5-e7c2-4d09-935e-d3c79c5903a1", "match_id": "203748c9-3fff-4d7f-83b8-22f0d9adc402", "map_id": "AmbroseValley", "x": -15.07, "z": -290.0, "px": 403.83, "py": 815.79, "ts": 1770780068, "event": "Loot", "is_bot": false, "is_combat": true, "rel_ts": 53}, {"user_id": "c830d8d5-e7c2-4d09-935e-d3c79c5903a1", "match_id": "203748c9-3fff-4d7f-83b8-22f0d9adc402", "map_id": "AmbroseValley", "x": -15.07, "z": -290.0, "px": 403.83, "py": 815.79, "ts": 1770780068, "event": "Loot", "is_bot": false, "is_combat": true, "rel_ts": 53}, {"user_id": "c830d8d5-e7c2-4d09-935e-d3c79c5903a1", "match_id": "203748c9-3fff-4d7f-83b8-22f0d9adc402", "map_id": "AmbroseValley", "x": -11.3, "z": -289.84, "px": 408.12, "py": 815.61, "ts": 1770780070, "event": "Position", "is_bot": false, "is_combat": false, "rel_ts": 55}, {"user_id": "c830d8d5-e7c2-4d09-935e-d3c79c5903a1", "match_id": "203748c9-3fff-4d7f-83b8-22f0d9adc402", "map_id": "AmbroseValley", "x": -2.83, "z": -282.0, "px": 417.76, "py": 806.68, "ts": 1770780073, "event": "Loot", "is_bot": false, "is_combat": true, "rel_ts": 58}, {"user_id": "c830d8d5-e7c2-4d09-935e-d3c79c5903a1", "match_id": "203748c9-3fff-4d7f-83b8-22f0d9adc402", "map_id": "AmbroseValley", "x": -2.64, "z": -278.98, "px": 417.98, "py": 803.25, "ts": 1770780075, "event": "Position", "is_bot": false, "is_combat": false, "rel_ts": 60}, {"user_id": "c830d8d5-e7c2-4d09-935e-d3c79c5903a1", "match_id": "203748c9-3fff-4d7f-83b8-22f0d9adc402", "map_id": "AmbroseValley", "x": -11.76, "z": -273.94, "px": 407.59, "py": 797.51, "ts": 1770780078, "event": "Loot", "is_bot": false, "is_combat": true, "rel_ts": 63}, {"user_id": "c830d8d5-e7c2-4d09-935e-d3c79c5903a1", "match_id": "203748c9-3fff-4d7f-83b8-22f0d9adc402", "map_id": "AmbroseValley", "x": -11.23, "z": -281.72, "px": 408.2, "py": 806.36, "ts": 1770780080, "event": "Position", "is_bot": false, "is_combat": false, "rel_ts": 65}, {"user_id": "c830d8d5-e7c2-4d09-935e-d3c79c5903a1", "match_id": "203748c9-3fff-4d7f-83b8-22f0d9adc402", "map_id": "AmbroseValley", "x": -17.69, "z": -281.05, "px": 400.85, "py": 805.6, "ts": 1770780083, "event": "Loot", "is_bot": false, "is_combat": true, "rel_ts": 68}, {"user_id": "c830d8d5-e7c2-4d09-935e-d3c79c5903a1", "match_id": "203748c9-3fff-4d7f-83b8-22f0d9adc402", "map_id": "AmbroseValley", "x": -8.08, "z": -277.85, "px": 411.79, "py": 801.97, "ts": 1770780090, "event": "Position", "is_bot": false, "is_combat": false, "rel_ts": 75}, {"user_id": "c830d8d5-e7c2-4d09-935e-d3c79c5903a1", "match_id": "203748c9-3fff-4d7f-83b8-22f0d9adc402", "map_id": "AmbroseValley", "x": -0.06, "z": -274.0, "px": 420.91, "py": 797.58, "ts": 1770780095, "event": "Position", "is_bot": false, "is_combat": false, "rel_ts": 80}, {"user_id": "c830d8d5-e7c2-4d09-935e-d3c79c5903a1", "match_id": "203748c9-3fff-4d7f-83b8-22f0d9adc402", "map_id": "AmbroseValley", "x": 22.11, "z": -283.09, "px": 446.13, "py": 807.92, "ts": 1770780100, "event": "Position", "is_bot": false, "is_combat": false, "rel_ts": 85}, {"user_id": "c830d8d5-e7c2-4d09-935e-d3c79c5903a1", "match_id": "203748c9-3fff-4d7f-83b8-22f0d9adc402", "map_id": "AmbroseValley", "x": 34.38, "z": -285.6, "px": 460.1, "py": 810.78, "ts": 1770780104, "event": "BotKill", "is_bot": false, "is_combat": true, "rel_ts": 89}, {"user_id": "c830d8d5-e7c2-4d09-935e-d3c79c5903a1", "match_id": "203748c9-3fff-4d7f-83b8-22f0d9adc402", "map_id": "AmbroseValley", "x": 34.38, "z": -285.6, "px": 460.1, "py": 810.78, "ts": 1770780105, "event": "Position", "is_bot": false, "is_combat": false, "rel_ts": 90}, {"user_id": "c830d8d5-e7c2-4d09-935e-d3c79c5903a1", "match_id": "203748c9-3fff-4d7f-83b8-22f0d9adc402", "map_id": "AmbroseValley", "x": 36.35, "z": -286.07, "px": 462.33, "py": 811.31, "ts": 1770780110, "event": "Position", "is_bot": false, "is_combat": false, "rel_ts": 95}, {"user_id": "c830d8d5-e7c2-4d09-935e-d3c79c5903a1", "match_id": "203748c9-3fff-4d7f-83b8-22f0d9adc402", "map_id": "AmbroseValley", "x": 48.16, "z": -287.41, "px": 475.77, "py": 812.84, "ts": 1770780114, "event": "Loot", "is_bot": false, "is_combat": true, "rel_ts": 99}, {"user_id": "c830d8d5-e7c2-4d09-935e-d3c79c5903a1", "match_id": "203748c9-3fff-4d7f-83b8-22f0d9adc402", "map_id": "AmbroseValley", "x": 48.16, "z": -287.41, "px": 475.77, "py": 812.84, "ts": 1770780114, "event": "Loot", "is_bot": false, "is_combat": true, "rel_ts": 99}, {"user_id": "c830d8d5-e7c2-4d09-935e-d3c79c5903a1", "match_id": "203748c9-3fff-4d7f-83b8-22f0d9adc402", "map_id": "AmbroseValley", "x": 49.9, "z": -286.21, "px": 477.76, "py": 811.47, "ts": 1770780115, "event": "Position", "is_bot": false, "is_combat": false, "rel_ts": 100}, {"user_id": "c830d8d5-e7c2-4d09-935e-d3c79c5903a1", "match_id": "203748c9-3fff-4d7f-83b8-22f0d9adc402", "map_id": "AmbroseValley", "x": 54.32, "z": -289.15, "px": 482.78, "py": 814.82, "ts": 1770780119, "event": "Loot", "is_bot": false, "is_combat": true, "rel_ts": 104}, {"user_id": "c830d8d5-e7c2-4d09-935e-d3c79c5903a1", "match_id": "203748c9-3fff-4d7f-83b8-22f0d9adc402", "map_id": "AmbroseValley", "x": 58.13, "z": -285.53, "px": 487.12, "py": 810.7, "ts": 1770780120, "event": "Position", "is_bot": false, "is_combat": false, "rel_ts": 105}, {"user_id": "c830d8d5-e7c2-4d09-935e-d3c79c5903a1", "match_id": "203748c9-3fff-4d7f-83b8-22f0d9adc402", "map_id": "AmbroseValley", "x": 81.62, "z": -278.86, "px": 513.85, "py": 803.11, "ts": 1770780125, "event": "Position", "is_bot": false, "is_combat": false, "rel_ts": 110}, {"user_id": "c830d8d5-e7c2-4d09-935e-d3c79c5903a1", "match_id": "203748c9-3fff-4d7f-83b8-22f0d9adc402", "map_id": "AmbroseValley", "x": 81.87, "z": -279.07, "px": 514.12, "py": 803.35, "ts": 1770780126, "event": "BotKill", "is_bot": false, "is_combat": true, "rel_ts": 111}, {"user_id": "c830d8d5-e7c2-4d09-935e-d3c79c5903a1", "match_id": "203748c9-3fff-4d7f-83b8-22f0d9adc402", "map_id": "AmbroseValley", "x": 83.85, "z": -272.15, "px": 516.38, "py": 795.48, "ts": 1770780129, "event": "Loot", "is_bot": false, "is_combat": true, "rel_ts": 114}, {"user_id": "c830d8d5-e7c2-4d09-935e-d3c79c5903a1", "match_id": "203748c9-3fff-4d7f-83b8-22f0d9adc402", "map_id": "AmbroseValley", "x": 83.85, "z": -272.15, "px": 516.38, "py": 795.48, "ts": 1770780130, "event": "Loot", "is_bot": false, "is_combat": true, "rel_ts": 115}, {"user_id": "c830d8d5-e7c2-4d09-935e-d3c79c5903a1", "match_id": "203748c9-3fff-4d7f-83b8-22f0d9adc402", "map_id": "AmbroseValley", "x": 84.14, "z": -271.68, "px": 516.71, "py": 794.95, "ts": 1770780130, "event": "Position", "is_bot": false, "is_combat": false, "rel_ts": 115}, {"user_id": "c830d8d5-e7c2-4d09-935e-d3c79c5903a1", "match_id": "203748c9-3fff-4d7f-83b8-22f0d9adc402", "map_id": "AmbroseValley", "x": 94.8, "z": -273.75, "px": 528.84, "py": 797.3, "ts": 1770780135, "event": "Position", "is_bot": false, "is_combat": false, "rel_ts": 120}, {"user_id": "c830d8d5-e7c2-4d09-935e-d3c79c5903a1", "match_id": "203748c9-3fff-4d7f-83b8-22f0d9adc402", "map_id": "AmbroseValley", "x": 104.99, "z": -268.1, "px": 540.43, "py": 790.87, "ts": 1770780140, "event": "Position", "is_bot": false, "is_combat": false, "rel_ts": 125}, {"user_id": "c830d8d5-e7c2-4d09-935e-d3c79c5903a1", "match_id": "203748c9-3fff-4d7f-83b8-22f0d9adc402", "map_id": "AmbroseValley", "x": 104.99, "z": -268.1, "px": 540.43, "py": 790.87, "ts": 1770780141, "event": "BotKill", "is_bot": false, "is_combat": true, "rel_ts": 126}, {"user_id": "c830d8d5-e7c2-4d09-935e-d3c79c5903a1", "match_id": "203748c9-3fff-4d7f-83b8-22f0d9adc402", "map_id": "AmbroseValley", "x": 112.59, "z": -278.69, "px": 549.08, "py": 802.92, "ts": 1770780145, "event": "Position", "is_bot": false, "is_combat": false, "rel_ts": 130}, {"user_id": "c830d8d5-e7c2-4d09-935e-d3c79c5903a1", "match_id": "203748c9-3fff-4d7f-83b8-22f0d9adc402", "map_id": "AmbroseValley", "x": 117.77, "z": -285.57, "px": 554.97, "py": 810.75, "ts": 1770780149, "event": "Loot", "is_bot": false, "is_combat": true, "rel_ts": 134}, {"user_id": "c830d8d5-e7c2-4d09-935e-d3c79c5903a1", "match_id": "203748c9-3fff-4d7f-83b8-22f0d9adc402", "map_id": "AmbroseValley", "x": 118.79, "z": -285.36, "px": 556.13, "py": 810.51, "ts": 1770780150, "event": "Position", "is_bot": false, "is_combat": false, "rel_ts": 135}, {"user_id": "c830d8d5-e7c2-4d09-935e-d3c79c5903a1", "match_id": "203748c9-3fff-4d7f-83b8-22f0d9adc402", "map_id": "AmbroseValley", "x": 118.73, "z": -285.41, "px": 556.06, "py": 810.57, "ts": 1770780152, "event": "Loot", "is_bot": false, "is_combat": true, "rel_ts": 137}, {"user_id": "c830d8d5-e7c2-4d09-935e-d3c79c5903a1", "match_id": "203748c9-3fff-4d7f-83b8-22f0d9adc402", "map_id": "AmbroseValley", "x": 119.29, "z": -284.97, "px": 556.7, "py": 810.07, "ts": 1770780154, "event": "Loot", "is_bot": false, "is_combat": true, "rel_ts": 139}, {"user_id": "c830d8d5-e7c2-4d09-935e-d3c79c5903a1", "match_id": "203748c9-3fff-4d7f-83b8-22f0d9adc402", "map_id": "AmbroseValley", "x": 114.8, "z": -282.18, "px": 551.59, "py": 806.89, "ts": 1770780160, "event": "Position", "is_bot": false, "is_combat": false, "rel_ts": 145}, {"user_id": "c830d8d5-e7c2-4d09-935e-d3c79c5903a1", "match_id": "203748c9-3fff-4d7f-83b8-22f0d9adc402", "map_id": "AmbroseValley", "x": 97.27, "z": -263.5, "px": 531.65, "py": 785.64, "ts": 1770780165, "event": "Position", "is_bot": false, "is_combat": false, "rel_ts": 150}, {"user_id": "c830d8d5-e7c2-4d09-935e-d3c79c5903a1", "match_id": "203748c9-3fff-4d7f-83b8-22f0d9adc402", "map_id": "AmbroseValley", "x": 98.48, "z": -265.11, "px": 533.02, "py": 787.47, "ts": 1770780166, "event": "Loot", "is_bot": false, "is_combat": true, "rel_ts": 151}, {"user_id": "c830d8d5-e7c2-4d09-935e-d3c79c5903a1", "match_id": "203748c9-3fff-4d7f-83b8-22f0d9adc402", "map_id": "AmbroseValley", "x": 92.71, "z": -262.22, "px": 526.46, "py": 784.18, "ts": 1770780169, "event": "Loot", "is_bot": false, "is_combat": true, "rel_ts": 154}, {"user_id": "c830d8d5-e7c2-4d09-935e-d3c79c5903a1", "match_id": "203748c9-3fff-4d7f-83b8-22f0d9adc402", "map_id": "AmbroseValley", "x": 92.71, "z": -262.22, "px": 526.46, "py": 784.18, "ts": 1770780170, "event": "Loot", "is_bot": false, "is_combat": true, "rel_ts": 155}, {"user_id": "c830d8d5-e7c2-4d09-935e-d3c79c5903a1", "match_id": "203748c9-3fff-4d7f-83b8-22f0d9adc402", "map_id": "AmbroseValley", "x": 93.98, "z": -261.45, "px": 527.9, "py": 783.3, "ts": 1770780170, "event": "Position", "is_bot": false, "is_combat": false, "rel_ts": 155}, {"user_id": "c830d8d5-e7c2-4d09-935e-d3c79c5903a1", "match_id": "203748c9-3fff-4d7f-83b8-22f0d9adc402", "map_id": "AmbroseValley", "x": 102.95, "z": -253.75, "px": 538.11, "py": 774.55, "ts": 1770780173, "event": "Loot", "is_bot": false, "is_combat": true, "rel_ts": 158}, {"user_id": "c830d8d5-e7c2-4d09-935e-d3c79c5903a1", "match_id": "203748c9-3fff-4d7f-83b8-22f0d9adc402", "map_id": "AmbroseValley", "x": 97.07, "z": -262.6, "px": 531.43, "py": 784.61, "ts": 1770780175, "event": "Position", "is_bot": false, "is_combat": false, "rel_ts": 160}, {"user_id": "c830d8d5-e7c2-4d09-935e-d3c79c5903a1", "match_id": "203748c9-3fff-4d7f-83b8-22f0d9adc402", "map_id": "AmbroseValley", "x": 92.28, "z": -253.22, "px": 525.97, "py": 773.94, "ts": 1770780181, "event": "Position", "is_bot": false, "is_combat": false, "rel_ts": 166}, {"user_id": "c830d8d5-e7c2-4d09-935e-d3c79c5903a1", "match_id": "203748c9-3fff-4d7f-83b8-22f0d9adc402", "map_id": "AmbroseValley", "x": 85.66, "z": -235.24, "px": 518.44, "py": 753.49, "ts": 1770780186, "event": "Position", "is_bot": false, "is_combat": false, "rel_ts": 171}, {"user_id": "c830d8d5-e7c2-4d09-935e-d3c79c5903a1", "match_id": "203748c9-3fff-4d7f-83b8-22f0d9adc402", "map_id": "AmbroseValley", "x": 82.62, "z": -217.85, "px": 514.98, "py": 733.7, "ts": 1770780191, "event": "Position", "is_bot": false, "is_combat": false, "rel_ts": 176}, {"user_id": "c830d8d5-e7c2-4d09-935e-d3c79c5903a1", "match_id": "203748c9-3fff-4d7f-83b8-22f0d9adc402", "map_id": "AmbroseValley", "x": 77.33, "z": -190.11, "px": 508.96, "py": 702.14, "ts": 1770780196, "event": "Position", "is_bot": false, "is_combat": false, "rel_ts": 181}, {"user_id": "c830d8d5-e7c2-4d09-935e-d3c79c5903a1", "match_id": "203748c9-3fff-4d7f-83b8-22f0d9adc402", "map_id": "AmbroseValley", "x": 76.72, "z": -181.98, "px": 508.27, "py": 692.89, "ts": 1770780201, "event": "Position", "is_bot": false, "is_combat": false, "rel_ts": 186}, {"user_id": "c830d8d5-e7c2-4d09-935e-d3c79c5903a1", "match_id": "203748c9-3fff-4d7f-83b8-22f0d9adc402", "map_id": "AmbroseValley", "x": 76.86, "z": -178.97, "px": 508.43, "py": 689.46, "ts": 1770780206, "event": "Position", "is_bot": false, "is_combat": false, "rel_ts": 191}, {"user_id": "c830d8d5-e7c2-4d09-935e-d3c79c5903a1", "match_id": "203748c9-3fff-4d7f-83b8-22f0d9adc402", "map_id": "AmbroseValley", "x": 76.1, "z": -160.86, "px": 507.56, "py": 668.85, "ts": 1770780226, "event": "Position", "is_bot": false, "is_combat": false, "rel_ts": 211}, {"user_id": "c830d8d5-e7c2-4d09-935e-d3c79c5903a1", "match_id": "203748c9-3fff-4d7f-83b8-22f0d9adc402", "map_id": "AmbroseValley", "x": 89.6, "z": -138.89, "px": 522.92, "py": 643.86, "ts": 1770780231, "event": "Position", "is_bot": false, "is_combat": false, "rel_ts": 216}, {"user_id": "c830d8d5-e7c2-4d09-935e-d3c79c5903a1", "match_id": "203748c9-3fff-4d7f-83b8-22f0d9adc402", "map_id": "AmbroseValley", "x": 95.36, "z": -113.64, "px": 529.48, "py": 615.13, "ts": 1770780236, "event": "Position", "is_bot": false, "is_combat": false, "rel_ts": 221}, {"user_id": "c830d8d5-e7c2-4d09-935e-d3c79c5903a1", "match_id": "203748c9-3fff-4d7f-83b8-22f0d9adc402", "map_id": "AmbroseValley", "x": 102.48, "z": -96.03, "px": 537.57, "py": 595.09, "ts": 1770780241, "event": "Position", "is_bot": false, "is_combat": false, "rel_ts": 226}, {"user_id": "c830d8d5-e7c2-4d09-935e-d3c79c5903a1", "match_id": "203748c9-3fff-4d7f-83b8-22f0d9adc402", "map_id": "AmbroseValley", "x": 102.48, "z": -96.03, "px": 537.57, "py": 595.09, "ts": 1770780242, "event": "Loot", "is_bot": false, "is_combat": true, "rel_ts": 227}, {"user_id": "c830d8d5-e7c2-4d09-935e-d3c79c5903a1", "match_id": "203748c9-3fff-4d7f-83b8-22f0d9adc402", "map_id": "AmbroseValley", "x": 102.48, "z": -96.03, "px": 537.57, "py": 595.09, "ts": 1770780242, "event": "Loot", "is_bot": false, "is_combat": true, "rel_ts": 227}, {"user_id": "c830d8d5-e7c2-4d09-935e-d3c79c5903a1", "match_id": "203748c9-3fff-4d7f-83b8-22f0d9adc402", "map_id": "AmbroseValley", "x": 101.82, "z": -97.56, "px": 536.83, "py": 596.84, "ts": 1770780247, "event": "BotKill", "is_bot": false, "is_combat": true, "rel_ts": 232}, {"user_id": "c830d8d5-e7c2-4d09-935e-d3c79c5903a1", "match_id": "203748c9-3fff-4d7f-83b8-22f0d9adc402", "map_id": "AmbroseValley", "x": 105.5, "z": -86.08, "px": 541.02, "py": 583.77, "ts": 1770780251, "event": "Position", "is_bot": false, "is_combat": false, "rel_ts": 236}, {"user_id": "c830d8d5-e7c2-4d09-935e-d3c79c5903a1", "match_id": "203748c9-3fff-4d7f-83b8-22f0d9adc402", "map_id": "AmbroseValley", "x": 106.61, "z": -83.57, "px": 542.28, "py": 580.91, "ts": 1770780253, "event": "Loot", "is_bot": false, "is_combat": true, "rel_ts": 238}, {"user_id": "c830d8d5-e7c2-4d09-935e-d3c79c5903a1", "match_id": "203748c9-3fff-4d7f-83b8-22f0d9adc402", "map_id": "AmbroseValley", "x": 109.05, "z": -78.97, "px": 545.05, "py": 575.68, "ts": 1770780255, "event": "Loot", "is_bot": false, "is_combat": true, "rel_ts": 240}, {"user_id": "c830d8d5-e7c2-4d09-935e-d3c79c5903a1", "match_id": "203748c9-3fff-4d7f-83b8-22f0d9adc402", "map_id": "AmbroseValley", "x": 109.05, "z": -78.97, "px": 545.05, "py": 575.68, "ts": 1770780255, "event": "Loot", "is_bot": false, "is_combat": true, "rel_ts": 240}, {"user_id": "c830d8d5-e7c2-4d09-935e-d3c79c5903a1", "match_id": "203748c9-3fff-4d7f-83b8-22f0d9adc402", "map_id": "AmbroseValley", "x": 107.06, "z": -78.15, "px": 542.79, "py": 574.75, "ts": 1770780256, "event": "Position", "is_bot": false, "is_combat": false, "rel_ts": 241}, {"user_id": "c830d8d5-e7c2-4d09-935e-d3c79c5903a1", "match_id": "203748c9-3fff-4d7f-83b8-22f0d9adc402", "map_id": "AmbroseValley", "x": 97.12, "z": -83.33, "px": 531.48, "py": 580.64, "ts": 1770780261, "event": "Position", "is_bot": false, "is_combat": false, "rel_ts": 246}, {"user_id": "c830d8d5-e7c2-4d09-935e-d3c79c5903a1", "match_id": "203748c9-3fff-4d7f-83b8-22f0d9adc402", "map_id": "AmbroseValley", "x": 93.31, "z": -82.5, "px": 527.15, "py": 579.7, "ts": 1770780266, "event": "Position", "is_bot": false, "is_combat": false, "rel_ts": 251}, {"user_id": "c830d8d5-e7c2-4d09-935e-d3c79c5903a1", "match_id": "203748c9-3fff-4d7f-83b8-22f0d9adc402", "map_id": "AmbroseValley", "x": 91.64, "z": -82.67, "px": 525.24, "py": 579.89, "ts": 1770780271, "event": "Loot", "is_bot": false, "is_combat": true, "rel_ts": 256}, {"user_id": "c830d8d5-e7c2-4d09-935e-d3c79c5903a1", "match_id": "203748c9-3fff-4d7f-83b8-22f0d9adc402", "map_id": "AmbroseValley", "x": 98.07, "z": -67.56, "px": 532.56, "py": 562.7, "ts": 1770780275, "event": "Loot", "is_bot": false, "is_combat": true, "rel_ts": 260}, {"user_id": "c830d8d5-e7c2-4d09-935e-d3c79c5903a1", "match_id": "203748c9-3fff-4d7f-83b8-22f0d9adc402", "map_id": "AmbroseValley", "x": 101.92, "z": -68.6, "px": 536.94, "py": 563.88, "ts": 1770780276, "event": "Position", "is_bot": false, "is_combat": false, "rel_ts": 261}, {"user_id": "c830d8d5-e7c2-4d09-935e-d3c79c5903a1", "match_id": "203748c9-3fff-4d7f-83b8-22f0d9adc402", "map_id": "AmbroseValley", "x": 95.87, "z": -87.3, "px": 530.06, "py": 585.16, "ts": 1770780281, "event": "Position", "is_bot": false, "is_combat": false, "rel_ts": 266}, {"user_id": "c830d8d5-e7c2-4d09-935e-d3c79c5903a1", "match_id": "203748c9-3fff-4d7f-83b8-22f0d9adc402", "map_id": "AmbroseValley", "x": 92.23, "z": -84.04, "px": 525.92, "py": 581.44, "ts": 1770780285, "event": "Loot", "is_bot": false, "is_combat": true, "rel_ts": 270}, {"user_id": "c830d8d5-e7c2-4d09-935e-d3c79c5903a1", "match_id": "203748c9-3fff-4d7f-83b8-22f0d9adc402", "map_id": "AmbroseValley", "x": 90.58, "z": -84.96, "px": 524.03, "py": 582.49, "ts": 1770780286, "event": "Position", "is_bot": false, "is_combat": false, "rel_ts": 271}, {"user_id": "c830d8d5-e7c2-4d09-935e-d3c79c5903a1", "match_id": "203748c9-3fff-4d7f-83b8-22f0d9adc402", "map_id": "AmbroseValley", "x": 87.87, "z": -77.21, "px": 520.96, "py": 573.68, "ts": 1770780291, "event": "Position", "is_bot": false, "is_combat": false, "rel_ts": 276}, {"user_id": "c830d8d5-e7c2-4d09-935e-d3c79c5903a1", "match_id": "203748c9-3fff-4d7f-83b8-22f0d9adc402", "map_id": "AmbroseValley", "x": 91.44, "z": -77.13, "px": 525.01, "py": 573.59, "ts": 1770780301, "event": "Position", "is_bot": false, "is_combat": false, "rel_ts": 286}, {"user_id": "c830d8d5-e7c2-4d09-935e-d3c79c5903a1", "match_id": "203748c9-3fff-4d7f-83b8-22f0d9adc402", "map_id": "AmbroseValley", "x": 91.44, "z": -77.13, "px": 525.01, "py": 573.59, "ts": 1770780304, "event": "Loot", "is_bot": false, "is_combat": true, "rel_ts": 289}, {"user_id": "c830d8d5-e7c2-4d09-935e-d3c79c5903a1", "match_id": "203748c9-3fff-4d7f-83b8-22f0d9adc402", "map_id": "AmbroseValley", "x": 88.01, "z": -74.73, "px": 521.12, "py": 570.86, "ts": 1770780311, "event": "Position", "is_bot": false, "is_combat": false, "rel_ts": 296}, {"user_id": "c830d8d5-e7c2-4d09-935e-d3c79c5903a1", "match_id": "203748c9-3fff-4d7f-83b8-22f0d9adc402", "map_id": "AmbroseValley", "x": 92.23, "z": -58.21, "px": 525.92, "py": 552.06, "ts": 1770780316, "event": "Position", "is_bot": false, "is_combat": false, "rel_ts": 301}, {"user_id": "c830d8d5-e7c2-4d09-935e-d3c79c5903a1", "match_id": "203748c9-3fff-4d7f-83b8-22f0d9adc402", "map_id": "AmbroseValley", "x": 92.23, "z": -58.21, "px": 525.92, "py": 552.06, "ts": 1770780317, "event": "Loot", "is_bot": false, "is_combat": true, "rel_ts": 302}, {"user_id": "c830d8d5-e7c2-4d09-935e-d3c79c5903a1", "match_id": "203748c9-3fff-4d7f-83b8-22f0d9adc402", "map_id": "AmbroseValley", "x": 92.23, "z": -58.21, "px": 525.92, "py": 552.06, "ts": 1770780318, "event": "Loot", "is_bot": false, "is_combat": true, "rel_ts": 303}, {"user_id": "c830d8d5-e7c2-4d09-935e-d3c79c5903a1", "match_id": "203748c9-3fff-4d7f-83b8-22f0d9adc402", "map_id": "AmbroseValley", "x": 102.98, "z": -54.84, "px": 538.15, "py": 548.23, "ts": 1770780321, "event": "Position", "is_bot": false, "is_combat": false, "rel_ts": 306}, {"user_id": "c830d8d5-e7c2-4d09-935e-d3c79c5903a1", "match_id": "203748c9-3fff-4d7f-83b8-22f0d9adc402", "map_id": "AmbroseValley", "x": 104.9, "z": -48.65, "px": 540.33, "py": 541.19, "ts": 1770780336, "event": "Position", "is_bot": false, "is_combat": false, "rel_ts": 321}, {"user_id": "c830d8d5-e7c2-4d09-935e-d3c79c5903a1", "match_id": "203748c9-3fff-4d7f-83b8-22f0d9adc402", "map_id": "AmbroseValley", "x": 105.55, "z": -48.23, "px": 541.07, "py": 540.71, "ts": 1770780341, "event": "Position", "is_bot": false, "is_combat": false, "rel_ts": 326}, {"user_id": "c830d8d5-e7c2-4d09-935e-d3c79c5903a1", "match_id": "203748c9-3fff-4d7f-83b8-22f0d9adc402", "map_id": "AmbroseValley", "x": 103.33, "z": -45.84, "px": 538.55, "py": 537.99, "ts": 1770780346, "event": "Position", "is_bot": false, "is_combat": false, "rel_ts": 331}, {"user_id": "c830d8d5-e7c2-4d09-935e-d3c79c5903a1", "match_id": "203748c9-3fff-4d7f-83b8-22f0d9adc402", "map_id": "AmbroseValley", "x": 101.59, "z": -50.4, "px": 536.56, "py": 543.17, "ts": 1770780362, "event": "Position", "is_bot": false, "is_combat": false, "rel_ts": 347}, {"user_id": "c830d8d5-e7c2-4d09-935e-d3c79c5903a1", "match_id": "203748c9-3fff-4d7f-83b8-22f0d9adc402", "map_id": "AmbroseValley", "x": 104.99, "z": -49.15, "px": 540.43, "py": 541.76, "ts": 1770780367, "event": "Position", "is_bot": false, "is_combat": false, "rel_ts": 352}, {"user_id": "c830d8d5-e7c2-4d09-935e-d3c79c5903a1", "match_id": "203748c9-3fff-4d7f-83b8-22f0d9adc402", "map_id": "AmbroseValley", "x": 104.93, "z": -50.24, "px": 540.37, "py": 542.99, "ts": 1770780372, "event": "Position", "is_bot": false, "is_combat": false, "rel_ts": 357}, {"user_id": "c830d8d5-e7c2-4d09-935e-d3c79c5903a1", "match_id": "203748c9-3fff-4d7f-83b8-22f0d9adc402", "map_id": "AmbroseValley", "x": 105.13, "z": -49.46, "px": 540.59, "py": 542.1, "ts": 1770780377, "event": "Position", "is_bot": false, "is_combat": false, "rel_ts": 362}, {"user_id": "c830d8d5-e7c2-4d09-935e-d3c79c5903a1", "match_id": "203748c9-3fff-4d7f-83b8-22f0d9adc402", "map_id": "AmbroseValley", "x": 102.89, "z": -48.97, "px": 538.04, "py": 541.55, "ts": 1770780387, "event": "Position", "is_bot": false, "is_combat": false, "rel_ts": 372}, {"user_id": "c830d8d5-e7c2-4d09-935e-d3c79c5903a1", "match_id": "203748c9-3fff-4d7f-83b8-22f0d9adc402", "map_id": "AmbroseValley", "x": 106.02, "z": -48.27, "px": 541.61, "py": 540.75, "ts": 1770780392, "event": "Position", "is_bot": false, "is_combat": false, "rel_ts": 377}, {"user_id": "c830d8d5-e7c2-4d09-935e-d3c79c5903a1", "match_id": "203748c9-3fff-4d7f-83b8-22f0d9adc402", "map_id": "AmbroseValley", "x": 104.91, "z": -52.21, "px": 540.34, "py": 545.23, "ts": 1770780397, "event": "Position", "is_bot": false, "is_combat": false, "rel_ts": 382}, {"user_id": "c830d8d5-e7c2-4d09-935e-d3c79c5903a1", "match_id": "203748c9-3fff-4d7f-83b8-22f0d9adc402", "map_id": "AmbroseValley", "x": 105.01, "z": -51.43, "px": 540.46, "py": 544.35, "ts": 1770780399, "event": "Loot", "is_bot": false, "is_combat": true, "rel_ts": 384}, {"user_id": "c830d8d5-e7c2-4d09-935e-d3c79c5903a1", "match_id": "203748c9-3fff-4d7f-83b8-22f0d9adc402", "map_id": "AmbroseValley", "x": 105.01, "z": -51.43, "px": 540.46, "py": 544.35, "ts": 1770780402, "event": "Position", "is_bot": false, "is_combat": false, "rel_ts": 387}, {"user_id": "c830d8d5-e7c2-4d09-935e-d3c79c5903a1", "match_id": "203748c9-3fff-4d7f-83b8-22f0d9adc402", "map_id": "AmbroseValley", "x": 117.13, "z": -52.62, "px": 554.25, "py": 545.7, "ts": 1770780412, "event": "Position", "is_bot": false, "is_combat": false, "rel_ts": 397}, {"user_id": "c830d8d5-e7c2-4d09-935e-d3c79c5903a1", "match_id": "203748c9-3fff-4d7f-83b8-22f0d9adc402", "map_id": "AmbroseValley", "x": 142.61, "z": -59.27, "px": 583.24, "py": 553.27, "ts": 1770780417, "event": "Position", "is_bot": false, "is_combat": false, "rel_ts": 402}, {"user_id": "c830d8d5-e7c2-4d09-935e-d3c79c5903a1", "match_id": "203748c9-3fff-4d7f-83b8-22f0d9adc402", "map_id": "AmbroseValley", "x": 153.53, "z": -61.9, "px": 595.66, "py": 556.26, "ts": 1770780420, "event": "Loot", "is_bot": false, "is_combat": true, "rel_ts": 405}, {"user_id": "c830d8d5-e7c2-4d09-935e-d3c79c5903a1", "match_id": "203748c9-3fff-4d7f-83b8-22f0d9adc402", "map_id": "AmbroseValley", "x": 159.28, "z": -61.13, "px": 602.21, "py": 555.38, "ts": 1770780422, "event": "Loot", "is_bot": false, "is_combat": true, "rel_ts": 407}, {"user_id": "c830d8d5-e7c2-4d09-935e-d3c79c5903a1", "match_id": "203748c9-3fff-4d7f-83b8-22f0d9adc402", "map_id": "AmbroseValley", "x": 159.25, "z": -61.26, "px": 602.17, "py": 555.53, "ts": 1770780422, "event": "Position", "is_bot": false, "is_combat": false, "rel_ts": 407}, {"user_id": "c830d8d5-e7c2-4d09-935e-d3c79c5903a1", "match_id": "203748c9-3fff-4d7f-83b8-22f0d9adc402", "map_id": "AmbroseValley", "x": 167.43, "z": -70.56, "px": 611.48, "py": 566.12, "ts": 1770780427, "event": "Position", "is_bot": false, "is_combat": false, "rel_ts": 412}, {"user_id": "c830d8d5-e7c2-4d09-935e-d3c79c5903a1", "match_id": "203748c9-3fff-4d7f-83b8-22f0d9adc402", "map_id": "AmbroseValley", "x": 158.36, "z": -77.75, "px": 601.16, "py": 574.29, "ts": 1770780431, "event": "Loot", "is_bot": false, "is_combat": true, "rel_ts": 416}, {"user_id": "c830d8d5-e7c2-4d09-935e-d3c79c5903a1", "match_id": "203748c9-3fff-4d7f-83b8-22f0d9adc402", "map_id": "AmbroseValley", "x": 159.06, "z": -76.97, "px": 601.95, "py": 573.41, "ts": 1770780432, "event": "Position", "is_bot": false, "is_combat": false, "rel_ts": 417}, {"user_id": "c830d8d5-e7c2-4d09-935e-d3c79c5903a1", "match_id": "203748c9-3fff-4d7f-83b8-22f0d9adc402", "map_id": "AmbroseValley", "x": 152.56, "z": -71.04, "px": 594.55, "py": 566.66, "ts": 1770780437, "event": "Position", "is_bot": false, "is_combat": false, "rel_ts": 422}, {"user_id": "c830d8d5-e7c2-4d09-935e-d3c79c5903a1", "match_id": "203748c9-3fff-4d7f-83b8-22f0d9adc402", "map_id": "AmbroseValley", "x": 149.01, "z": -66.11, "px": 590.52, "py": 561.05, "ts": 1770780438, "event": "Loot", "is_bot": false, "is_combat": true, "rel_ts": 423}, {"user_id": "c830d8d5-e7c2-4d09-935e-d3c79c5903a1", "match_id": "203748c9-3fff-4d7f-83b8-22f0d9adc402", "map_id": "AmbroseValley", "x": 148.41, "z": -77.65, "px": 589.83, "py": 574.19, "ts": 1770780442, "event": "Position", "is_bot": false, "is_combat": false, "rel_ts": 427}, {"user_id": "c830d8d5-e7c2-4d09-935e-d3c79c5903a1", "match_id": "203748c9-3fff-4d7f-83b8-22f0d9adc402", "map_id": "AmbroseValley", "x": 140.69, "z": -79.79, "px": 581.05, "py": 576.62, "ts": 1770780447, "event": "Position", "is_bot": false, "is_combat": false, "rel_ts": 432}, {"user_id": "c830d8d5-e7c2-4d09-935e-d3c79c5903a1", "match_id": "203748c9-3fff-4d7f-83b8-22f0d9adc402", "map_id": "AmbroseValley", "x": 147.18, "z": -93.93, "px": 588.44, "py": 592.7, "ts": 1770780452, "event": "Position", "is_bot": false, "is_combat": false, "rel_ts": 437}, {"user_id": "c830d8d5-e7c2-4d09-935e-d3c79c5903a1", "match_id": "203748c9-3fff-4d7f-83b8-22f0d9adc402", "map_id": "AmbroseValley", "x": 148.74, "z": -95.06, "px": 590.21, "py": 593.99, "ts": 1770780456, "event": "Loot", "is_bot": false, "is_combat": true, "rel_ts": 441}, {"user_id": "c830d8d5-e7c2-4d09-935e-d3c79c5903a1", "match_id": "203748c9-3fff-4d7f-83b8-22f0d9adc402", "map_id": "AmbroseValley", "x": 148.86, "z": -90.9, "px": 590.35, "py": 589.25, "ts": 1770780462, "event": "Loot", "is_bot": false, "is_combat": true, "rel_ts": 447}, {"user_id": "c830d8d5-e7c2-4d09-935e-d3c79c5903a1", "match_id": "203748c9-3fff-4d7f-83b8-22f0d9adc402", "map_id": "AmbroseValley", "x": 142.22, "z": -88.04, "px": 582.8, "py": 586.0, "ts": 1770780467, "event": "Position", "is_bot": false, "is_combat": false, "rel_ts": 452}, {"user_id": "c830d8d5-e7c2-4d09-935e-d3c79c5903a1", "match_id": "203748c9-3fff-4d7f-83b8-22f0d9adc402", "map_id": "AmbroseValley", "x": 126.42, "z": -69.35, "px": 564.81, "py": 564.74, "ts": 1770780472, "event": "Position", "is_bot": false, "is_combat": false, "rel_ts": 457}, {"user_id": "c830d8d5-e7c2-4d09-935e-d3c79c5903a1", "match_id": "203748c9-3fff-4d7f-83b8-22f0d9adc402", "map_id": "AmbroseValley", "x": 118.41, "z": -71.43, "px": 555.71, "py": 567.11, "ts": 1770780477, "event": "Position", "is_bot": false, "is_combat": false, "rel_ts": 462}, {"user_id": "c830d8d5-e7c2-4d09-935e-d3c79c5903a1", "match_id": "203748c9-3fff-4d7f-83b8-22f0d9adc402", "map_id": "AmbroseValley", "x": 100.13, "z": -93.08, "px": 534.91, "py": 591.73, "ts": 1770780482, "event": "Position", "is_bot": false, "is_combat": false, "rel_ts": 467}, {"user_id": "c830d8d5-e7c2-4d09-935e-d3c79c5903a1", "match_id": "203748c9-3fff-4d7f-83b8-22f0d9adc402", "map_id": "AmbroseValley", "x": 98.23, "z": -94.66, "px": 532.74, "py": 593.54, "ts": 1770780487, "event": "Position", "is_bot": false, "is_combat": false, "rel_ts": 472}, {"user_id": "c830d8d5-e7c2-4d09-935e-d3c79c5903a1", "match_id": "203748c9-3fff-4d7f-83b8-22f0d9adc402", "map_id": "AmbroseValley", "x": 98.51, "z": -95.26, "px": 533.06, "py": 594.22, "ts": 1770780492, "event": "Position", "is_bot": false, "is_combat": false, "rel_ts": 477}, {"user_id": "c830d8d5-e7c2-4d09-935e-d3c79c5903a1", "match_id": "203748c9-3fff-4d7f-83b8-22f0d9adc402", "map_id": "AmbroseValley", "x": 98.51, "z": -95.26, "px": 533.06, "py": 594.22, "ts": 1770780492, "event": "BotKill", "is_bot": false, "is_combat": true, "rel_ts": 477}, {"user_id": "c830d8d5-e7c2-4d09-935e-d3c79c5903a1", "match_id": "203748c9-3fff-4d7f-83b8-22f0d9adc402", "map_id": "AmbroseValley", "x": 98.61, "z": -95.7, "px": 533.17, "py": 594.72, "ts": 1770780497, "event": "BotKill", "is_bot": false, "is_combat": true, "rel_ts": 482}, {"user_id": "c830d8d5-e7c2-4d09-935e-d3c79c5903a1", "match_id": "203748c9-3fff-4d7f-83b8-22f0d9adc402", "map_id": "AmbroseValley", "x": 98.61, "z": -95.7, "px": 533.17, "py": 594.72, "ts": 1770780498, "event": "BotKill", "is_bot": false, "is_combat": true, "rel_ts": 483}, {"user_id": "c830d8d5-e7c2-4d09-935e-d3c79c5903a1", "match_id": "203748c9-3fff-4d7f-83b8-22f0d9adc402", "map_id": "AmbroseValley", "x": 87.33, "z": -94.06, "px": 520.34, "py": 592.85, "ts": 1770780501, "event": "Loot", "is_bot": false, "is_combat": true, "rel_ts": 486}, {"user_id": "c830d8d5-e7c2-4d09-935e-d3c79c5903a1", "match_id": "203748c9-3fff-4d7f-83b8-22f0d9adc402", "map_id": "AmbroseValley", "x": 87.33, "z": -94.06, "px": 520.34, "py": 592.85, "ts": 1770780501, "event": "Loot", "is_bot": false, "is_combat": true, "rel_ts": 486}, {"user_id": "c830d8d5-e7c2-4d09-935e-d3c79c5903a1", "match_id": "203748c9-3fff-4d7f-83b8-22f0d9adc402", "map_id": "AmbroseValley", "x": 87.33, "z": -94.06, "px": 520.34, "py": 592.85, "ts": 1770780502, "event": "Loot", "is_bot": false, "is_combat": true, "rel_ts": 487}, {"user_id": "c830d8d5-e7c2-4d09-935e-d3c79c5903a1", "match_id": "203748c9-3fff-4d7f-83b8-22f0d9adc402", "map_id": "AmbroseValley", "x": 87.33, "z": -94.06, "px": 520.34, "py": 592.85, "ts": 1770780502, "event": "Loot", "is_bot": false, "is_combat": true, "rel_ts": 487}, {"user_id": "c830d8d5-e7c2-4d09-935e-d3c79c5903a1", "match_id": "203748c9-3fff-4d7f-83b8-22f0d9adc402", "map_id": "AmbroseValley", "x": 87.33, "z": -94.06, "px": 520.34, "py": 592.85, "ts": 1770780502, "event": "Position", "is_bot": false, "is_combat": false, "rel_ts": 487}, {"user_id": "c830d8d5-e7c2-4d09-935e-d3c79c5903a1", "match_id": "203748c9-3fff-4d7f-83b8-22f0d9adc402", "map_id": "AmbroseValley", "x": 75.9, "z": -97.48, "px": 507.33, "py": 596.74, "ts": 1770780506, "event": "Loot", "is_bot": false, "is_combat": true, "rel_ts": 491}, {"user_id": "c830d8d5-e7c2-4d09-935e-d3c79c5903a1", "match_id": "203748c9-3fff-4d7f-83b8-22f0d9adc402", "map_id": "AmbroseValley", "x": 75.9, "z": -97.48, "px": 507.33, "py": 596.74, "ts": 1770780506, "event": "Loot", "is_bot": false, "is_combat": true, "rel_ts": 491}, {"user_id": "c830d8d5-e7c2-4d09-935e-d3c79c5903a1", "match_id": "203748c9-3fff-4d7f-83b8-22f0d9adc402", "map_id": "AmbroseValley", "x": 71.81, "z": -102.8, "px": 502.68, "py": 602.8, "ts": 1770780507, "event": "Position", "is_bot": false, "is_combat": false, "rel_ts": 492}, {"user_id": "c830d8d5-e7c2-4d09-935e-d3c79c5903a1", "match_id": "203748c9-3fff-4d7f-83b8-22f0d9adc402", "map_id": "AmbroseValley", "x": 46.15, "z": -106.66, "px": 473.49, "py": 607.19, "ts": 1770780512, "event": "Position", "is_bot": false, "is_combat": false, "rel_ts": 497}, {"user_id": "c830d8d5-e7c2-4d09-935e-d3c79c5903a1", "match_id": "203748c9-3fff-4d7f-83b8-22f0d9adc402", "map_id": "AmbroseValley", "x": 29.86, "z": -106.29, "px": 454.96, "py": 606.77, "ts": 1770780517, "event": "Position", "is_bot": false, "is_combat": false, "rel_ts": 502}, {"user_id": "c830d8d5-e7c2-4d09-935e-d3c79c5903a1", "match_id": "203748c9-3fff-4d7f-83b8-22f0d9adc402", "map_id": "AmbroseValley", "x": 13.09, "z": -103.85, "px": 435.87, "py": 603.99, "ts": 1770780522, "event": "Position", "is_bot": false, "is_combat": false, "rel_ts": 507}, {"user_id": "c830d8d5-e7c2-4d09-935e-d3c79c5903a1", "match_id": "203748c9-3fff-4d7f-83b8-22f0d9adc402", "map_id": "AmbroseValley", "x": 20.49, "z": -109.9, "px": 444.29, "py": 610.88, "ts": 1770780527, "event": "Position", "is_bot": false, "is_combat": false, "rel_ts": 512}, {"user_id": "c830d8d5-e7c2-4d09-935e-d3c79c5903a1", "match_id": "203748c9-3fff-4d7f-83b8-22f0d9adc402", "map_id": "AmbroseValley", "x": 20.85, "z": -131.42, "px": 444.7, "py": 635.35, "ts": 1770780533, "event": "Position", "is_bot": false, "is_combat": false, "rel_ts": 518}, {"user_id": "c830d8d5-e7c2-4d09-935e-d3c79c5903a1", "match_id": "203748c9-3fff-4d7f-83b8-22f0d9adc402", "map_id": "AmbroseValley", "x": 5.31, "z": -155.86, "px": 427.02, "py": 663.16, "ts": 1770780538, "event": "Position", "is_bot": false, "is_combat": false, "rel_ts": 523}, {"user_id": "c830d8d5-e7c2-4d09-935e-d3c79c5903a1", "match_id": "203748c9-3fff-4d7f-83b8-22f0d9adc402", "map_id": "AmbroseValley", "x": 15.97, "z": -179.01, "px": 439.14, "py": 689.5, "ts": 1770780543, "event": "Position", "is_bot": false, "is_combat": false, "rel_ts": 528}, {"user_id": "c830d8d5-e7c2-4d09-935e-d3c79c5903a1", "match_id": "203748c9-3fff-4d7f-83b8-22f0d9adc402", "map_id": "AmbroseValley", "x": 22.17, "z": -196.21, "px": 446.21, "py": 709.07, "ts": 1770780548, "event": "Position", "is_bot": false, "is_combat": false, "rel_ts": 533}, {"user_id": "c830d8d5-e7c2-4d09-935e-d3c79c5903a1", "match_id": "203748c9-3fff-4d7f-83b8-22f0d9adc402", "map_id": "AmbroseValley", "x": 38.19, "z": -213.25, "px": 464.43, "py": 728.46, "ts": 1770780553, "event": "Position", "is_bot": false, "is_combat": false, "rel_ts": 538}, {"user_id": "c830d8d5-e7c2-4d09-935e-d3c79c5903a1", "match_id": "203748c9-3fff-4d7f-83b8-22f0d9adc402", "map_id": "AmbroseValley", "x": 52.47, "z": -237.43, "px": 480.68, "py": 755.97, "ts": 1770780558, "event": "Position", "is_bot": false, "is_combat": false, "rel_ts": 543}, {"user_id": "c830d8d5-e7c2-4d09-935e-d3c79c5903a1", "match_id": "203748c9-3fff-4d7f-83b8-22f0d9adc402", "map_id": "AmbroseValley", "x": 61.63, "z": -255.87, "px": 491.1, "py": 776.95, "ts": 1770780563, "event": "Position", "is_bot": false, "is_combat": false, "rel_ts": 548}, {"user_id": "c830d8d5-e7c2-4d09-935e-d3c79c5903a1", "match_id": "203748c9-3fff-4d7f-83b8-22f0d9adc402", "map_id": "AmbroseValley", "x": 73.08, "z": -282.31, "px": 504.12, "py": 807.04, "ts": 1770780568, "event": "Position", "is_bot": false, "is_combat": false, "rel_ts": 553}, {"user_id": "c830d8d5-e7c2-4d09-935e-d3c79c5903a1", "match_id": "203748c9-3fff-4d7f-83b8-22f0d9adc402", "map_id": "AmbroseValley", "x": 73.11, "z": -303.6, "px": 504.16, "py": 831.26, "ts": 1770780573, "event": "Position", "is_bot": false, "is_combat": false, "rel_ts": 558}, {"user_id": "c830d8d5-e7c2-4d09-935e-d3c79c5903a1", "match_id": "203748c9-3fff-4d7f-83b8-22f0d9adc402", "map_id": "AmbroseValley", "x": 73.88, "z": -308.57, "px": 505.04, "py": 836.92, "ts": 1770780588, "event": "Position", "is_bot": false, "is_combat": false, "rel_ts": 573}]